snowplow_tracker/__init__.py
snowplow_tracker/_version.py
snowplow_tracker/emitters.py
snowplow_tracker/payload.py
snowplow_tracker/redis_worker.py
snowplow_tracker/self_describing_json.py
snowplow_tracker/subject.py
snowplow_tracker/tracker.py
datacoral_tracker_py-0.0.12.dist-info/LICENSE-2.0.txt
datacoral_tracker_py-0.0.12.dist-info/METADATA
datacoral_tracker_py-0.0.12.dist-info/WHEEL
datacoral_tracker_py-0.0.12.dist-info/top_level.txt
datacoral_tracker_py-0.0.12.dist-info/RECORD
