Metadata-Version: 2.1
Name: datacoral-tracker-py
Version: 0.0.12
Summary: Datacoral's Python Instrumentation using Snowplow
Home-page: http://datacoral.com
Author: Datacoral
Author-email: support@datacoral.co
License: Apache License 2.0
Platform: UNKNOWN
Classifier: Development Status :: 4 - Beta
Classifier: Intended Audience :: Developers
Classifier: License :: OSI Approved :: Apache Software License
Classifier: Programming Language :: Python
Requires-Dist: requests
Requires-Dist: pycontracts
Requires-Dist: gevent
Requires-Dist: redis
